{"geometries":[{"data":{"castShadow":true,"doubleSided":true,"faces":[0,0,1,2,0,2,3,0,0,4,5,6,0,6,7,4,0,3,2,4,0,4,7,3,0,0,3,6,0,7,6,3,0,1,0,6,0,6,5,1,0,2,1,4,0,5,4,1],"normals":[],"scale":1,"uvs":[],"vertices":[-73426,37109,100186,-73426,37160,100186,-73409,37160,100287,-73409,37109,100287,-74508,37160,100474,-74525,37160,100374,-74525,37109,100374,-74508,37109,100474],"visible":true},"type":"Geometry","uuid":"d9a4ec3f-e1bf-4141-9f79-cc097e66b68c-0003f074-4f46423f-5c26-11d4-9217-0000863f27ad-00004a09"}],"materials":[{"ambient":16250871,"color":16250871,"emissive":0,"name":"Metal - Aluminum","opacity":1,"shininess":128,"specular":16250871,"transparent":false,"type":"MeshPhongMaterial","uuid":"4f46423f-5c26-11d4-9217-0000863f27ad-00004a09","wireframe":false}],"metadata":{"generator":"YouBIM Json exporter","type":"Object","version":1},"object":{"GUID":"d645a228-2190-42d3-9b2a-469e9f6648b2-001a67d2","children":[{"GUID":"d9a4ec3f-e1bf-4141-9f79-cc097e66b68c-0003f074","children":[{"GUID":"d9a4ec3f-e1bf-4141-9f79-cc097e66b68c-0003f074-4f46423f-5c26-11d4-9217-0000863f27ad-00004a09","geometry":"d9a4ec3f-e1bf-4141-9f79-cc097e66b68c-0003f074-4f46423f-5c26-11d4-9217-0000863f27ad-00004a09","material":"4f46423f-5c26-11d4-9217-0000863f27ad-00004a09","matrix":[1,0,0,0,0,1,0,0,0,0,1,0,0,0,0,1],"name":"Mullion Curtain Wall Mullions Rectangular Mullion <258164 2\" x 4\" rectangular>","type":"Mesh"}],"material":"4f46423f-5c26-11d4-9217-0000863f27ad-00004a09","matrix":[1,0,0,0,0,1,0,0,0,0,1,0,0,0,0,1],"name":"Mullion Curtain Wall Mullions Rectangular Mullion <258164 2\" x 4\" rectangular>","type":"RevitElement"}],"matrix":[0.01,0,0,0,0,0.01,0,0,0,0,0.01,0,0,0,0,0.01],"name":"BIM Wellington_Architecture.rvt","type":"Object3D"}}